{
  "patterns": [
    {
      "time": "2026-06-19T18:31:26.227995",
      "equity": 1000.0
    }
  ],
  "trades": [],
  "decisions": [],
  "pending_orders": [
    {
      "id": "cdbc5e1b-4e9f-4c7c-b0b5-4fbdfcbe8813",
      "symbol": "VOO",
      "side": "buy",
      "qty": 0,
      "price": 688.1099853515625,
      "time": "2026-06-19T18:31:26.227995"
    },
    {
      "id": "6a9ffcf5-1fb7-47a6-a304-6b14ed2ce334",
      "symbol": "SPY",
      "side": "buy",
      "qty": 0,
      "price": 746.739990234375,
      "time": "2026-06-19T18:31:26.227995"
    },
    {
      "id": "8ffa2b4e-60bd-4e9b-81dc-4556e7e91d6e",
      "symbol": "QQQ",
      "side": "buy",
      "qty": 0,
      "price": 740.6199951171875,
      "time": "2026-06-19T18:31:26.227995"
    },
    {
      "id": "2bc568cf-ac17-4062-9c72-80d5d4ded487",
      "symbol": "AMD",
      "side": "buy",
      "qty": 0,
      "price": 537.3699951171875,
      "time": "2026-06-19T18:31:26.227995"
    },
    {
      "id": "7ab9a190-ad25-4569-acaf-0ef7196b6e8f",
      "symbol": "TSM",
      "side": "buy",
      "qty": 0,
      "price": 462.1199951171875,
      "time": "2026-06-19T18:31:26.227995"
    },
    {
      "id": "3b73c286-e1fe-466e-a276-cd330a58e61c",
      "symbol": "TLT",
      "side": "buy",
      "qty": 0,
      "price": 86.75,
      "time": "2026-06-19T18:31:26.227995"
    }
  ],
  "start_equity": 1000,
  "last_equity": 1000
}